[
  {
    "name": "NWMT",
    "id": "nwmt",
    "years": [
      { "year": "2016" },
      { "year": "2015" },
      { "year": "2014" },
      { "year": "2013" },
      { "year": "2012" },
      { "year": "2011" }
    ]
  },
  {
    "name": "NWSMT",
    "id": "nwsmt",
    "years": [
      { "year": "2016" },
      { "year": "2015" }
    ]
  },
  {
    "name": "VMRS",
    "id": "mrs",
    "years": [
      { "year": "2016" },
      { "year": "2015" }
    ]
  },
  {
    "name": "SK Mods",
    "id": "sk",
    "years": [
      { "year": "2016" },
      { "year": "2015" }
    ]
  },
  {
    "name": "Mods",
    "id": "mods"
  },
  {
    "name": "Utilities",
    "id": "utils"
  }
]
